Organisms/__init__.py
Organisms/GA/Cluster.py
Organisms/GA/Collection.py
Organisms/GA/Collections_Iterator.py
Organisms/GA/Crossover.py
Organisms/GA/EnergyProfile.py
Organisms/GA/Epoch.py
Organisms/GA/ExternalDefinitions.py
Organisms/GA/GA_Initiate.py
Organisms/GA/GA_Introducing_Remarks.py
Organisms/GA/GA_Program.py
Organisms/GA/GA_Program_Details.py
Organisms/GA/GA_Program_external_methods.py
Organisms/GA/GA_Recording_System.py
Organisms/GA/GA_Setup.py
Organisms/GA/Get_Offspring.py
Organisms/GA/Get_Predation_and_Fitness_Operators.py
Organisms/GA/Initialise_Population.py
Organisms/GA/Lock.py
Organisms/GA/Memory_Operator.py
Organisms/GA/Mutation.py
Organisms/GA/Offspring_Pool.py
Organisms/GA/Population.py
Organisms/GA/Surface.py
Organisms/GA/Timer.py
Organisms/GA/Types_Of_Mutations.py
Organisms/GA/check_version_of_asap3.py
Organisms/GA/exitting_procedure.py
Organisms/GA/Fitness_Operators/CNA_Database_Check.py
Organisms/GA/Fitness_Operators/CNA_Fitness_Contribution.py
Organisms/GA/Fitness_Operators/Dynamics_Mode.py
Organisms/GA/Fitness_Operators/Energetic_Fitness_Contribution.py
Organisms/GA/Fitness_Operators/Energy_Fitness_Operator.py
Organisms/GA/Fitness_Operators/Fitness_Function.py
Organisms/GA/Fitness_Operators/Fitness_Operator.py
Organisms/GA/Fitness_Operators/SCM_and_Energy_Fitness_Operator.py
Organisms/GA/Fitness_Operators/SCM_and_Energy_Fitness_Operator_Options.py
Organisms/GA/Predation_Operators/Energy_Predation_Operator.py
Organisms/GA/Predation_Operators/IDCM_Predation_Operator.py
Organisms/GA/Predation_Operators/No_Predation_Operator.py
Organisms/GA/Predation_Operators/Predation_Operator.py
Organisms/GA/Predation_Operators/SCM_Predation_Operator.py
Organisms/GA/Predation_Operators/Energy_Predation_Operator_Scripts/Comprehensive_Energy_Predation_Operator_energy.py
Organisms/GA/Predation_Operators/Energy_Predation_Operator_Scripts/Comprehensive_Energy_Predation_Operator_fitness.py
Organisms-3.2.7.1.dist-info/LICENSE
Organisms-3.2.7.1.dist-info/METADATA
Organisms-3.2.7.1.dist-info/WHEEL
Organisms-3.2.7.1.dist-info/top_level.txt
Organisms-3.2.7.1.dist-info/RECORD
