Metadata-Version: 2.1
Name: Organisms
Version: 3.2.7.1
Summary: This program is designed to perform a genetic algorithm global optimisation for nanoclusters.
Home-page: https://blogs.otago.ac.nz/annagarden/
Author: Geoffrey R. Weal and Dr. Anna L. Garden
Author-email: anna.garden@otago.ac.nz
License: GNU AFFERO GENERAL PUBLIC LICENSE
Download-URL: https://github.com/GardenGroupUO/Organisms/archive/v3.2.7.1.tar.gz
Keywords: nanoclusters,nanoparticles,clusters,optimisation,genetic-algorithm,ase,university-of-otago,asap3,atomic-simulation-environment,jupyter-binder,predation-operator,fitness-operator,otago-university,common-neighbor-analysis,common-neighbour-analysis
Platform: UNKNOWN
Classifier: Development Status :: 3 - Alpha
Classifier: Intended Audience :: Science/Research
Classifier: Natural Language :: English
Classifier: Operating System :: MacOS :: MacOS X
Classifier: Operating System :: POSIX :: Linux
Classifier: Operating System :: Unix
Classifier: Topic :: Scientific/Engineering :: Chemistry
Classifier: Topic :: Scientific/Engineering :: Physics
Classifier: Topic :: Scientific/Engineering :: Mathematics
Classifier: Topic :: Scientific/Engineering :: Artificial Intelligence
Classifier: Natural Language :: English
Classifier: License :: OSI Approved :: GNU Affero General Public License v3
Classifier: Programming Language :: Python :: 3 :: Only
Classifier: Programming Language :: Python :: 3.6
Classifier: Programming Language :: Python :: 3.7
Classifier: Programming Language :: Python :: 3.8
Classifier: Programming Language :: Python :: 3.9
Requires-Dist: numpy
Requires-Dist: scipy
Requires-Dist: ase (>=3.21.1)
Requires-Dist: asap3 (==3.11.10)
Requires-Dist: Sphinx
Requires-Dist: sphinx-rtd-theme
Requires-Dist: sphinx-tabs
Requires-Dist: sphinxcontrib-applehelp
Requires-Dist: sphinxcontrib-devhelp
Requires-Dist: sphinxcontrib-htmlhelp
Requires-Dist: sphinxcontrib-jsmath
Requires-Dist: sphinxcontrib-plantuml
Requires-Dist: sphinxcontrib-qthelp
Requires-Dist: sphinxcontrib-serializinghtml
Requires-Dist: sphinxcontrib-wiki
Requires-Dist: packaging
Requires-Dist: termcolor
